am4894pd/__init__.py
am4894pd/am4894pd.py
am4894pd/checks.py
am4894pd/utils.py
am4894pd-0.1.6.dist-info/AUTHORS.rst
am4894pd-0.1.6.dist-info/LICENSE
am4894pd-0.1.6.dist-info/METADATA
am4894pd-0.1.6.dist-info/WHEEL
am4894pd-0.1.6.dist-info/top_level.txt
am4894pd-0.1.6.dist-info/RECORD
